Workbook

Sheet Visão Geral
A1: Overdrive - Planejamento Scrum
A2: Equipe: Alan Filipe, Gustavo Lona e Pedro Moraes. Células em azul são premissas que podem ser alteradas.
A3: Papel | B3: Pessoa | C3: Responsabilidade
A4: Product Owner | B4: Pedro Moraes | C4: Dono do backlog do produto: prioriza os itens e aceita (ou não) as entregas na Review.
A5: Scrum Master | B5: Alan Filipe | C5: Facilita as cerimônias, remove impedimentos e garante que o time siga o Scrum.
A6: Time de Desenvolvimento | B6: Alan Filipe, Gustavo Lona e Pedro Moraes | C6: Planeja, constrói e testa o incremento de cada sprint.
A8: Parâmetros de custo
A9: Valor da hora de desenvolvimento (R$) | B9: 35 | C9: Premissa da equipe (estimativa), não é salário real.
A11: Sprint | B11: Nome | C11: Início | D11: Fim | E11: Dias úteis | F11: Pontos | G11: Horas | H11: Custo (R$) | I11: Meta da sprint
A12: 0 | B12: Sprint 0 - Planejamento e Requisitos | C12: 46307 | D12: 46316 | E12: =NETWORKDAYS(C12,D12) -> 8 | F12: =SUMIF('Backlog do Produto'!$G:$G,A12,'Backlog do Produto'!$F:$F) -> 0 | G12: =SUMIF('Backlog da Sprint'!$C:$C,A12,'Backlog da Sprint'!$G:$G) -> 0 | H12: =G12*$B$9 -> 0 | I12: Levantar requisitos, modelar o sistema e montar o backlog e o quadro Kanban.
A13: 1 | B13: Sprint 1 - Base do sistema | C13: 46317 | D13: 46323 | E13: =NETWORKDAYS(C13,D13) -> 5 | F13: =SUMIF('Backlog do Produto'!$G:$G,A13,'Backlog do Produto'!$F:$F) -> 24 | G13: =SUMIF('Backlog da Sprint'!$C:$C,A13,'Backlog da Sprint'!$G:$G) -> 72 | H13: =G13*$B$9 -> 2520 | I13: Ter a base do sistema rodando, com login por perfil e cadastro de clientes e veículos.
A14: 2 | B14: Sprint 2 - Ordem de Serviço | C14: 46324 | D14: 46330 | E14: =NETWORKDAYS(C14,D14) -> 5 | F14: =SUMIF('Backlog do Produto'!$G:$G,A14,'Backlog do Produto'!$F:$F) -> 26 | G14: =SUMIF('Backlog da Sprint'!$C:$C,A14,'Backlog da Sprint'!$G:$G) -> 78 | H14: =G14*$B$9 -> 2730 | I14: Abrir uma OS completa (com checklist), consultar histórico, agendar atendimentos e cadastrar peças.
A15: 3 | B15: Sprint 3 - Ciclo da OS | C15: 46331 | D15: 46337 | E15: =NETWORKDAYS(C15,D15) -> 5 | F15: =SUMIF('Backlog do Produto'!$G:$G,A15,'Backlog do Produto'!$F:$F) -> 26 | G15: =SUMIF('Backlog da Sprint'!$C:$C,A15,'Backlog da Sprint'!$G:$G) -> 78 | H15: =G15*$B$9 -> 2730 | I15: Fechar o ciclo da OS: orçamento, aprovação, status e encerramento com baixa de estoque.
A16: 4 | B16: Sprint 4 - Gestão e entrega | C16: 46338 | D16: 46344 | E16: =NETWORKDAYS(C16,D16) -> 5 | F16: =SUMIF('Backlog do Produto'!$G:$G,A16,'Backlog do Produto'!$F:$F) -> 26 | G16: =SUMIF('Backlog da Sprint'!$C:$C,A16,'Backlog da Sprint'!$G:$G) -> 78 | H16: =G16*$B$9 -> 2730 | I16: Completar notificações, alertas, financeiro e relatórios; testar e preparar a entrega final.
A17: - | B17: Sem sprint (fora do prazo) | F17: =SUMIF('Backlog do Produto'!$G:$G,A17,'Backlog do Produto'!$F:$F) -> 5 | G17: =SUMIF('Backlog da Sprint'!$C:$C,A17,'Backlog da Sprint'!$G:$G) -> 15 | H17: =G17*$B$9 -> 525 | I17: Backup e auditoria ficam para depois da entrega, se sobrar tempo.
B18: Total | F18: =SUM(F12:F17) -> 107 | G18: =SUM(G12:G17) -> 321 | H18: =SUM(H12:H17) -> 11235
A20: Custos de infraestrutura (opcional)
A21: Item | B21: Valor unitário (R$) | C21: Quantidade | D21: Unidade | E21: Total (R$)
A22: Hospedagem do sistema (servidor/VPS) | B22: 50 | C22: 2 | D22: mês | E22: =B22*C22 -> 100
A23: Domínio .com.br | B23: 40 | C23: 1 | D23: ano | E23: =B23*C23 -> 40
A24: API de WhatsApp/e-mail (plano de testes) | B24: 0 | C24: 1 | D24: período | E24: =B24*C24 -> 0
A25: Total infraestrutura | E25: =SUM(E22:E24) -> 140
A26: Custo total provável (mão de obra + infraestrutura) | E26: =H18+E25 -> 11375

Sheet Backlog do Produto
A1: Backlog do Produto
A2: Itens ordenados por sprint. Horas e custo vêm da aba Backlog da Sprint (fórmulas).
A3: ID | B3: Épico | C3: História de usuário | D3: Requisitos | E3: Prioridade | F3: Pontos | G3: Sprint | H3: Responsável | I3: Status | J3: Horas | K3: Custo (R$)
A4: PB01 | B4: Infraestrutura | C4: Como time, quero configurar o ambiente, o repositório e o banco de dados, para começar a desenvolver com a base organizada. | D4: RNF14 | E4: Alta | F4: 3 | G4: 1 | H4: Gustavo Lona | I4: A fazer | J4: =SUMIF('Backlog da Sprint'!$B:$B,A4,'Backlog da Sprint'!$G:$G) -> 9 | K4: =J4*'Visão Geral'!$B$9 -> 315
A5: PB02 | B5: Infraestrutura | C5: Como time, quero modelar o banco de dados, para guardar clientes, veículos, OS, peças e contas de forma consistente. | D5: RF02, RF03, RF06, RF13, RF16 | E5: Alta | F5: 3 | G5: 1 | H5: Pedro Moraes | I5: A fazer | J5: =SUMIF('Backlog da Sprint'!$B:$B,A5,'Backlog da Sprint'!$G:$G) -> 9 | K5: =J5*'Visão Geral'!$B$9 -> 315
A6: PB03 | B6: Acesso e Segurança | C6: Como funcionário, quero fazer login com usuário e senha, para acessar apenas as telas do meu perfil. | D6: RF01, RNF10, RNF11 | E6: Alta | F6: 5 | G6: 1 | H6: Gustavo Lona | I6: A fazer | J6: =SUMIF('Backlog da Sprint'!$B:$B,A6,'Backlog da Sprint'!$G:$G) -> 15 | K6: =J6*'Visão Geral'!$B$9 -> 525
A7: PB04 | B7: Acesso e Segurança | C7: Como administrador, quero cadastrar funcionários e definir o perfil de cada um, para que cada pessoa veja só o que é da sua função. | D7: RF18, RF01 | E7: Média | F7: 3 | G7: 1 | H7: Pedro Moraes | I7: A fazer | J7: =SUMIF('Backlog da Sprint'!$B:$B,A7,'Backlog da Sprint'!$G:$G) -> 9 | K7: =J7*'Visão Geral'!$B$9 -> 315
A8: PB05 | B8: Cadastros | C8: Como recepcionista, quero cadastrar clientes com nome, CPF e telefone, para ter os dados à mão nos próximos atendimentos. | D8: RF02, RNF05 | E8: Alta | F8: 5 | G8: 1 | H8: Alan Filipe | I8: A fazer | J8: =SUMIF('Backlog da Sprint'!$B:$B,A8,'Backlog da Sprint'!$G:$G) -> 15 | K8: =J8*'Visão Geral'!$B$9 -> 525
A9: PB06 | B9: Cadastros | C9: Como recepcionista, quero cadastrar veículos vinculados a um cliente, para identificar rápido qual carro está sendo atendido. | D9: RF03, RNF05 | E9: Alta | F9: 5 | G9: 1 | H9: Alan Filipe | I9: A fazer | J9: =SUMIF('Backlog da Sprint'!$B:$B,A9,'Backlog da Sprint'!$G:$G) -> 15 | K9: =J9*'Visão Geral'!$B$9 -> 525
A10: PB07 | B10: Ordem de Serviço | C10: Como recepcionista, quero abrir uma OS informando placa, km e problema relatado, para registrar a entrada do veículo. | D10: RF06, RNF03, RNF09 | E10: Alta | F10: 8 | G10: 2 | H10: Gustavo Lona | I10: Backlog | J10: =SUMIF('Backlog da Sprint'!$B:$B,A10,'Backlog da Sprint'!$G:$G) -> 24 | K10: =J10*'Visão Geral'!$B$9 -> 840
A11: PB08 | B11: Ordem de Serviço | C11: Como recepcionista, quero registrar o checklist de entrada, para evitar discussões sobre danos que já existiam. | D11: RF07 | E11: Alta | F11: 5 | G11: 2 | H11: Pedro Moraes | I11: Backlog | J11: =SUMIF('Backlog da Sprint'!$B:$B,A11,'Backlog da Sprint'!$G:$G) -> 15 | K11: =J11*'Visão Geral'!$B$9 -> 525
A12: PB09 | B12: Ordem de Serviço | C12: Como mecânico, quero consultar o histórico de serviços de um veículo pela placa, para diagnosticar com base nas manutenções anteriores. | D12: RF04 | E12: Média | F12: 3 | G12: 2 | H12: Alan Filipe | I12: Backlog | J12: =SUMIF('Backlog da Sprint'!$B:$B,A12,'Backlog da Sprint'!$G:$G) -> 9 | K12: =J12*'Visão Geral'!$B$9 -> 315
A13: PB10 | B13: Ordem de Serviço | C13: Como recepcionista, quero agendar, reagendar e cancelar atendimentos, para organizar a entrada de carros e evitar lotação dos boxes. | D13: RF05 | E13: Média | F13: 5 | G13: 2 | H13: Alan Filipe | I13: Backlog | J13: =SUMIF('Backlog da Sprint'!$B:$B,A13,'Backlog da Sprint'!$G:$G) -> 15 | K13: =J13*'Visão Geral'!$B$9 -> 525
A14: PB15 | B14: Estoque | C14: Como administrador, quero cadastrar peças com código, preços, quantidade e estoque mínimo, para ter o estoque organizado. | D14: RF13 | E14: Alta | F14: 5 | G14: 2 | H14: Pedro Moraes | I14: Backlog | J14: =SUMIF('Backlog da Sprint'!$B:$B,A14,'Backlog da Sprint'!$G:$G) -> 15 | K14: =J14*'Visão Geral'!$B$9 -> 525
A15: PB11 | B15: Ordem de Serviço | C15: Como mecânico, quero montar o orçamento da OS com peças e mão de obra, para que o cliente saiba o valor antes de autorizar. | D15: RF08 | E15: Alta | F15: 8 | G15: 3 | H15: Gustavo Lona | I15: Backlog | J15: =SUMIF('Backlog da Sprint'!$B:$B,A15,'Backlog da Sprint'!$G:$G) -> 24 | K15: =J15*'Visão Geral'!$B$9 -> 840
... A25: PB23 | B25: Qualidade | C25: Como time, quero preparar a entrega final, para apresentar o sistema funcionando. | D25: - | E25: Média | F25: 3 | G25: 4 | H25: Pedro Moraes | I25: Backlog | J25: =SUMIF('Backlog da Sprint'!$B:$B,A25,'Backlog da Sprint'!$G:$G) -> 9 | K25: =J25*'Visão Geral'!$B$9 -> 315
A26: PB22 | B26: Qualidade | C26: Como administrador, quero backup automático e registro de auditoria, para recuperar dados e saber quem alterou o quê. | D26: RNF08, RNF12 | E26: Baixa | F26: 5 | G26: - | H26: A definir | I26: Backlog | J26: =SUMIF('Backlog da Sprint'!$B:$B,A26,'Backlog da Sprint'!$G:$G) -> 15 | K26: =J26*'Visão Geral'!$B$9 -> 525
C27: Total | F27: =SUM(F4:F26) -> 107 | J27: =SUM(J4:J26) -> 321 | K27: =SUM(K4:K26) -> 11235

Sheet Backlog da Sprint
A1: Backlog da Sprint (tarefas)
A2: Cada história do backlog do produto foi quebrada em tarefas. Início e fim vêm das datas da sprint.
A3: ID | B3: Item | C3: Sprint | D3: O que será feito | E3: Como será feito | F3: Responsável | G3: Horas | H3: Início | I3: Fim | J3: Status | K3: Custo (R$)
A4: S0-01 | B4: S0 | C4: 0 | D4: Definir a situação-problema e o funil de ideias | E4: Funil de ideias partindo do problema até a solução escolhida | F4: Equipe | H4: =IFERROR(INDEX('Visão Geral'!$C$12:$C$16,MATCH(C4,'Visão Geral'!$A$12:$A$16,0)),"A definir") -> 46307 | I4: =IFERROR(INDEX('Visão Geral'!$D$12:$D$16,MATCH(C4,'Visão Geral'!$A$12:$A$16,0)),"A definir") -> 46316 | J4: Concluído | K4: =G4*'Visão Geral'!$B$9 -> 0
A5: S0-02 | B5: S0 | C5: 0 | D5: Criar o questionário do cliente no Google Forms | E5: Google Forms com perfil, situação atual e prioridades | F5: Equipe | H5: =IFERROR(INDEX('Visão Geral'!$C$12:$C$16,MATCH(C5,'Visão Geral'!$A$12:$A$16,0)),"A definir") -> 46307 | I5: =IFERROR(INDEX('Visão Geral'!$D$12:$D$16,MATCH(C5,'Visão Geral'!$A$12:$A$16,0)),"A definir") -> 46316 | J5: Concluído | K5: =G5*'Visão Geral'!$B$9 -> 0
A6: S0-03 | B6: S0 | C6: 0 | D6: Elaborar os mapas mentais de ideias e de requisitos | E6: Mapa mental no Coggle | F6: Equipe | H6: =IFERROR(INDEX('Visão Geral'!$C$12:$C$16,MATCH(C6,'Visão Geral'!$A$12:$A$16,0)),"A definir") -> 46307 | I6: =IFERROR(INDEX('Visão Geral'!$D$12:$D$16,MATCH(C6,'Visão Geral'!$A$12:$A$16,0)),"A definir") -> 46316 | J6: Concluído | K6: =G6*'Visão Geral'!$B$9 -> 0
A7: S0-04 | B7: S0 | C7: 0 | D7: Elencar os requisitos do cliente e os requisitos funcionais e não funcionais | E7: RF01 a RF18 e RNF01 a RNF16, com ISO/IEC 25010 | F7: Equipe | H7: =IFERROR(INDEX('Visão Geral'!$C$12:$C$16,MATCH(C7,'Visão Geral'!$A$12:$A$16,0)),"A definir") -> 46307 | I7: =IFERROR(INDEX('Visão Geral'!$D$12:$D$16,MATCH(C7,'Visão Geral'!$A$12:$A$16,0)),"A definir") -> 46316 | J7: Concluído | K7: =G7*'Visão Geral'!$B$9 -> 0
A8: S0-05 | B8: S0 | C8: 0 | D8: Elaborar a modelagem UML (casos de uso, sequência e estados) | E8: Diagramas UML documentados | F8: Equipe | H8: =IFERROR(INDEX('Visão Geral'!$C$12:$C$16,MATCH(C8,'Visão Geral'!$A$12:$A$16,0)),"A definir") -> 46307 | I8: =IFERROR(INDEX('Visão Geral'!$D$12:$D$16,MATCH(C8,'Visão Geral'!$A$12:$A$16,0)),"A definir") -> 46316 | J8: Concluído | K8: =G8*'Visão Geral'!$B$9 -> 0
A9: S0-06 | B9: S0 | C9: 0 | D9: Modelar o processo de atendimento em BPMN | E9: Processo com raias: Cliente, Recepcionista, Mecânico e Sistema | F9: Equipe | H9: =IFERROR(INDEX('Visão Geral'!$C$12:$C$16,MATCH(C9,'Visão Geral'!$A$12:$A$16,0)),"A definir") -> 46307 | I9: =IFERROR(INDEX('Visão Geral'!$D$12:$D$16,MATCH(C9,'Visão Geral'!$A$12:$A$16,0)),"A definir") -> 46316 | J9: Concluído | K9: =G9*'Visão Geral'!$B$9 -> 0
A10: S0-07 | B10: S0 | C10: 0 | D10: Montar o backlog do produto, o backlog da sprint e o quadro Kanban no Trello | E10: Excel de apoio + quadro no Trello | F10: Equipe | H10: =IFERROR(INDEX('Visão Geral'!$C$12:$C$16,MATCH(C10,'Visão Geral'!$A$12:$A$16,0)),"A definir") -> 46307 | I10: =IFERROR(INDEX('Visão Geral'!$D$12:$D$16,MATCH(C10,'Visão Geral'!$A$12:$A$16,0)),"A definir") -> 46316 | J10: Em andamento | K10: =G10*'Visão Geral'!$B$9 -> 0
A11: S0-08 | B11: S0 | C11: 0 | D11: Preparar a apresentação do planejamento Scrum | E11: PPTX com os prints do Trello | F11: Equipe | H11: =IFERROR(INDEX('Visão Geral'!$C$12:$C$16,MATCH(C11,'Visão Geral'!$A$12:$A$16,0)),"A definir") -> 46307 | I11: =IFERROR(INDEX('Visão Geral'!$D$12:$D$16,MATCH(C11,'Visão Geral'!$A$12:$A$16,0)),"A definir") -> 46316 | J11: Em andamento | K11: =G11*'Visão Geral'!$B$9 -> 0
A12: PB01-T1 | B12: PB01 | C12: 1 | D12: Criar repositório Git e definir branches (main, dev e feature) | E12: GitHub, com pull request revisado por outro integrante | F12: Gustavo Lona | G12: 2 | H12: =IFERROR(INDEX('Visão Geral'!$C$12:$C$16,MATCH(C12,'Visão Geral'!$A$12:$A$16,0)),"A definir") -> 46317 | I12: =IFERROR(INDEX('Visão Geral'!$D$12:$D$16,MATCH(C12,'Visão Geral'!$A$12:$A$16,0)),"A definir") -> 46323 | J12: A fazer | K12: =G12*'Visão Geral'!$B$9 -> 70
A13: PB01-T2 | B13: PB01 | C13: 1 | D13: Configurar o ambiente e o projeto em camadas (apresentação, regras de negócio e dados) | E13: Framework web escolhido pela equipe, separando as camadas em módulos | F13: Gustavo Lona | G13: 4 | H13: =IFERROR(INDEX('Visão Geral'!$C$12:$C$16,MATCH(C13,'Visão Geral'!$A$12:$A$16,0)),"A definir") -> 46317 | I13: =IFERROR(INDEX('Visão Geral'!$D$12:$D$16,MATCH(C13,'Visão Geral'!$A$12:$A$16,0)),"A definir") -> 46323 | J13: A fazer | K13: =G13*'Visão Geral'!$B$9 -> 140
A14: PB01-T3 | B14: PB01 | C14: 1 | D14: Criar o banco de dados e o script de migração inicial | E14: Script SQL versionado no repositório | F14: Gustavo Lona | G14: 3 | H14: =IFERROR(INDEX('Visão Geral'!$C$12:$C$16,MATCH(C14,'Visão Geral'!$A$12:$A$16,0)),"A definir") -> 46317 | I14: =IFERROR(INDEX('Visão Geral'!$D$12:$D$16,MATCH(C14,'Visão Geral'!$A$12:$A$16,0)),"A definir") -> 46323 | J14: A fazer | K14: =G14*'Visão Geral'!$B$9 -> 105
A15: PB02-T1 | B15: PB02 | C15: 1 | D15: Elaborar o DER (cliente, veículo, OS, peça, funcionário e conta) | E15: Modelagem em ferramenta de diagramas, validada com os requisitos | F15: Pedro Moraes | G15: 4 | H15: =IFERROR(INDEX('Visão Geral'!$C$12:$C$16,MATCH(C15,'Visão Geral'!$A$12:$A$16,0)),"A definir") -> 46317 | I15: =IFERROR(INDEX('Visão Geral'!$D$12:$D$16,MATCH(C15,'Visão Geral'!$A$12:$A$16,0)),"A definir") -> 46323 | J15: A fazer | K15: =G15*'Visão Geral'!$B$9 -> 140
A16: PB02-T2 | B16: PB02 | C16: 1 | D16: Criar o dicionário de dados e os scripts DDL | E16: Documento + scripts SQL no repositório | F16: Pedro Moraes | G16: 3 | H16: =IFERROR(INDEX('Visão Geral'!$C$12:$C$16,MATCH(C16,'Visão Geral'!$A$12:$A$16,0)),"A definir") -> 46317 | I16: =IFERROR(INDEX('Visão Geral'!$D$12:$D$16,MATCH(C16,'Visão Geral'!$A$12:$A$16,0)),"A definir") -> 46323 | J16: A fazer | K16: =G16*'Visão Geral'!$B$9 -> 105
A17: PB02-T3 | B17: PB02 | C17: 1 | D17: Revisar o modelo com a equipe | E17: Reunião curta de revisão, ajustes registrados | F17: Pedro Moraes | G17: 2 | H17: =IFERROR(INDEX('Visão Geral'!$C$12:$C$16,MATCH(C17,'Visão Geral'!$A$12:$A$16,0)),"A definir") -> 46317 | I17: =IFERROR(INDEX('Visão Geral'!$D$12:$D$16,MATCH(C17,'Visão Geral'!$A$12:$A$16,0)),"A definir") -> 46323 | J17: A fazer | K17: =G17*'Visão Geral'!$B$9 -> 70
A18: PB03-T1 | B18: PB03 | C18: 1 | D18: Criar a tela de login e a validação de credenciais | E18: Formulário com validação no front e no back-end | F18: Gustavo Lona | G18: 5 | H18: =IFERROR(INDEX('Visão Geral'!$C$12:$C$16,MATCH(C18,'Visão Geral'!$A$12:$A$16,0)),"A definir") -> 46317 | I18: =IFERROR(INDEX('Visão Geral'!$D$12:$D$16,MATCH(C18,'Visão Geral'!$A$12:$A$16,0)),"A definir") -> 46323 | J18: A fazer | K18: =G18*'Visão Geral'!$B$9 -> 175
A19: PB03-T2 | B19: PB03 | C19: 1 | D19: Implementar hash de senha (bcrypt), sessão de 30 min e bloqueio após 5 tentativas | E19: Regras no módulo de autenticação, com testes unitários | F19: Gustavo Lona | G19: 6 | H19: =IFERROR(INDEX('Visão Geral'!$C$12:$C$16,MATCH(C19,'Visão Geral'!$A$12:$A$16,0)),"A definir") -> 46317 | I19: =IFERROR(INDEX('Visão Geral'!$D$12:$D$16,MATCH(C19,'Visão Geral'!$A$12:$A$16,0)),"A definir") -> 46323 | J19: A fazer | K19: =G19*'Visão Geral'!$B$9 -> 210
A20: PB03-T3 | B20: PB03 | C20: 1 | D20: Controlar o acesso às telas por perfil (Recepcionista, Mecânico e Administrador) | E20: Verificação de perfil em cada rota protegida | F20: Gustavo Lona | G20: 4 | H20: =IFERROR(INDEX('Visão Geral'!$C$12:$C$16,MATCH(C20,'Visão Geral'!$A$12:$A$16,0)),"A definir") -> 46317 | I20: =IFERROR(INDEX('Visão Geral'!$D$12:$D$16,MATCH(C20,'Visão Geral'!$A$12:$A$16,0)),"A definir") -> 46323 | J20: A fazer | K20: =G20*'Visão Geral'!$B$9 -> 140
A21: PB04-T1 | B21: PB04 | C21: 1 | D21: Criar o cadastro de funcionários (incluir, alterar e inativar) | E21: Tela CRUD ligada à tabela de funcionários | F21: Pedro Moraes | G21: 5 | H21: =IFERROR(INDEX('Visão Geral'!$C$12:$C$16,MATCH(C21,'Visão Geral'!$A$12:$A$16,0)),"A definir") -> 46317 | I21: =IFERROR(INDEX('Visão Geral'!$D$12:$D$16,MATCH(C21,'Visão Geral'!$A$12:$A$16,0)),"A definir") -> 46323 | J21: A fazer | K21: =G21*'Visão Geral'!$B$9 -> 175
A22: PB04-T2 | B22: PB04 | C22: 1 | D22: Atribuir o perfil de acesso ao funcionário | E22: Campo de perfil com lista fixa de três opções | F22: Pedro Moraes | G22: 2 | H22: =IFERROR(INDEX('Visão Geral'!$C$12:$C$16,MATCH(C22,'Visão Geral'!$A$12:$A$16,0)),"A definir") -> 46317 | I22: =IFERROR(INDEX('Visão Geral'!$D$12:$D$16,MATCH(C22,'Visão Geral'!$A$12:$A$16,0)),"A definir") -> 46323 | J22: A fazer | K22: =G22*'Visão Geral'!$B$9 -> 70
A23: PB04-T3 | B23: PB04 | C23: 1 | D23: Bloquear o login de funcionário inativado | E23: Validação de status no momento do login | F23: Pedro Moraes | G23: 2 | H23: =IFERROR(INDEX('Visão Geral'!$C$12:$C$16,MATCH(C23,'Visão Geral'!$A$12:$A$16,0)),"A definir") -> 46317 | I23: =IFERROR(INDEX('Visão Geral'!$D$12:$D$16,MATCH(C23,'Visão Geral'!$A$12:$A$16,0)),"A definir") -> 46323 | J23: A fazer | K23: =G23*'Visão Geral'!$B$9 -> 70
... A77: PB23-T3 | B77: PB23 | C77: 4 | D77: Ensaiar a apresentação final | E77: Ensaio com a equipe completa | F77: Pedro Moraes | G77: 2 | H77: =IFERROR(INDEX('Visão Geral'!$C$12:$C$16,MATCH(C77,'Visão Geral'!$A$12:$A$16,0)),"A definir") -> 46338 | I77: =IFERROR(INDEX('Visão Geral'!$D$12:$D$16,MATCH(C77,'Visão Geral'!$A$12:$A$16,0)),"A definir") -> 46344 | J77: Backlog | K77: =G77*'Visão Geral'!$B$9 -> 70
A78: PB22-T1 | B78: PB22 | C78: - | D78: Configurar o backup automático diário do banco | E78: Rotina agendada com cópia em local separado | F78: A definir | G78: 6 | H78: =IFERROR(INDEX('Visão Geral'!$C$12:$C$16,MATCH(C78,'Visão Geral'!$A$12:$A$16,0)),"A definir") -> A definir | I78: =IFERROR(INDEX('Visão Geral'!$D$12:$D$16,MATCH(C78,'Visão Geral'!$A$12:$A$16,0)),"A definir") -> A definir | J78: Backlog | K78: =G78*'Visão Geral'!$B$9 -> 210
A79: PB22-T2 | B79: PB22 | C79: - | D79: Registrar auditoria de OS, estoque e financeiro | E79: Tabela de auditoria com usuário, data e valores antes e depois | F79: A definir | G79: 6 | H79: =IFERROR(INDEX('Visão Geral'!$C$12:$C$16,MATCH(C79,'Visão Geral'!$A$12:$A$16,0)),"A definir") -> A definir | I79: =IFERROR(INDEX('Visão Geral'!$D$12:$D$16,MATCH(C79,'Visão Geral'!$A$12:$A$16,0)),"A definir") -> A definir | J79: Backlog | K79: =G79*'Visão Geral'!$B$9 -> 210
A80: PB22-T3 | B80: PB22 | C80: - | D80: Testar a restauração do backup | E80: Restauração em ambiente de teste | F80: A definir | G80: 3 | H80: =IFERROR(INDEX('Visão Geral'!$C$12:$C$16,MATCH(C80,'Visão Geral'!$A$12:$A$16,0)),"A definir") -> A definir | I80: =IFERROR(INDEX('Visão Geral'!$D$12:$D$16,MATCH(C80,'Visão Geral'!$A$12:$A$16,0)),"A definir") -> A definir | J80: Backlog | K80: =G80*'Visão Geral'!$B$9 -> 105
F81: Total | G81: =SUM(G4:G80) -> 321 | K81: =SUM(K4:K80) -> 11235

Sheet Cerimônias
A1: Cerimônias da Sprint
A2: Planejamento, execução, revisão e aprendizado.
A3: Cerimônia | B3: Quando | C3: Duração | D3: Participantes | E3: Objetivo | F3: Entrada | G3: Saída
A4: Sprint Planning (Planejamento) | B4: 1º dia da sprint | C4: 1h | D4: Time inteiro | E4: Definir a meta da sprint e escolher quais itens do backlog do produto entram na sprint. | F4: Backlog do produto priorizado e velocidade do time | G4: Backlog da sprint e meta da sprint
A5: Daily Scrum (Execução) | B5: Todo dia útil | C5: 15 min | D5: Time de desenvolvimento | E5: Alinhar o trabalho do dia: o que fiz, o que farei e o que me impede. | F5: Quadro Kanban atualizado no Trello | G5: Impedimentos registrados e cartões em dia
A6: Sprint Review (Revisão) | B6: Último dia da sprint | C6: 45 min | D6: Time e Product Owner | E6: Demonstrar o que foi entregue e verificar se cada item atende aos critérios de aceite. | F6: Incremento do sistema funcionando | G6: Itens aceitos e backlog do produto atualizado
A7: Sprint Retrospective (Aprendizado) | B7: Último dia da sprint, após a Review | C7: 30 min | D7: Time inteiro | E7: Refletir sobre o que funcionou, o que não funcionou e o que melhorar na próxima sprint. | F7: Dados da sprint (entregas, atrasos e impedimentos) | G7: Ações de melhoria para a próxima sprint
A9: Calendário das cerimônias (datas calculadas a partir das sprints)
A10: Sprint | B10: Planning (início) | C10: Daily (de) | D10: Daily (até) | E10: Review (fim) | F10: Retrospective (fim) | G10: Duração (dias úteis)
A11: ='Visão Geral'!B12 -> Sprint 0 - Planejamento e Requisitos | B11: ='Visão Geral'!C12 -> 46307 | C11: ='Visão Geral'!C12 -> 46307 | D11: ='Visão Geral'!D12 -> 46316 | E11: ='Visão Geral'!D12 -> 46316 | F11: ='Visão Geral'!D12 -> 46316 | G11: ='Visão Geral'!E12 -> 8
A12: ='Visão Geral'!B13 -> Sprint 1 - Base do sistema | B12: ='Visão Geral'!C13 -> 46317 | C12: ='Visão Geral'!C13 -> 46317 | D12: ='Visão Geral'!D13 -> 46323 | E12: ='Visão Geral'!D13 -> 46323 | F12: ='Visão Geral'!D13 -> 46323 | G12: ='Visão Geral'!E13 -> 5
A13: ='Visão Geral'!B14 -> Sprint 2 - Ordem de Serviço | B13: ='Visão Geral'!C14 -> 46324 | C13: ='Visão Geral'!C14 -> 46324 | D13: ='Visão Geral'!D14 -> 46330 | E13: ='Visão Geral'!D14 -> 46330 | F13: ='Visão Geral'!D14 -> 46330 | G13: ='Visão Geral'!E14 -> 5
A14: ='Visão Geral'!B15 -> Sprint 3 - Ciclo da OS | B14: ='Visão Geral'!C15 -> 46331 | C14: ='Visão Geral'!C15 -> 46331 | D14: ='Visão Geral'!D15 -> 46337 | E14: ='Visão Geral'!D15 -> 46337 | F14: ='Visão Geral'!D15 -> 46337 | G14: ='Visão Geral'!E15 -> 5
A15: ='Visão Geral'!B16 -> Sprint 4 - Gestão e entrega | B15: ='Visão Geral'!C16 -> 46338 | C15: ='Visão Geral'!C16 -> 46338 | D15: ='Visão Geral'!D16 -> 46344 | E15: ='Visão Geral'!D16 -> 46344 | F15: ='Visão Geral'!D16 -> 46344 | G15: ='Visão Geral'!E16 -> 5
A17: Registro da Sprint Review (preencher ao final de cada sprint)
A18: Sprint | B18: Itens entregues | C18: Itens aceitos pelo PO | D18: Itens não concluídos | E18: Feedback recebido | F18: Pontos entregues
A19: ='Visão Geral'!B12 -> Sprint 0 - Planejamento e Requisitos
A20: ='Visão Geral'!B13 -> Sprint 1 - Base do sistema
A21: ='Visão Geral'!B14 -> Sprint 2 - Ordem de Serviço
A22: ='Visão Geral'!B15 -> Sprint 3 - Ciclo da OS
A23: ='Visão Geral'!B16 -> Sprint 4 - Gestão e entrega
A25: Registro da Sprint Retrospective (preencher ao final de cada sprint)
A26: Sprint | B26: O que funcionou bem | C26: O que não funcionou | D26: O que vamos melhorar | E26: Responsável pela ação | F26: Prazo da ação
A27: ='Visão Geral'!B12 -> Sprint 0 - Planejamento e Requisitos
A28: ='Visão Geral'!B13 -> Sprint 1 - Base do sistema
A29: ='Visão Geral'!B14 -> Sprint 2 - Ordem de Serviço
A30: ='Visão Geral'!B15 -> Sprint 3 - Ciclo da OS
A31: ='Visão Geral'!B16 -> Sprint 4 - Gestão e entrega

Sheet Cartões Trello
A1: Cartões para o Trello
A2: Copie a coluna 'Título' de uma lista por vez e cole em 'Adicionar cartão' no Trello (uma linha vira um cartão). Veja a aba Guia Trello.
A3: Lista | B3: Título do cartão | C3: Descrição | D3: Etiqueta | E3: Membro | F3: Data de entrega | G3: Checklist (uma tarefa por item)
A4: Concluído | B4: S0-01 Definir a situação-problema e o funil de ideias | C4: Funil de ideias partindo do problema até a solução escolhida | D4: Sprint 0 | E4: Equipe | F4: 46316
A5: Concluído | B5: S0-02 Criar o questionário do cliente no Google Forms | C5: Google Forms com perfil, situação atual e prioridades | D5: Sprint 0 | E5: Equipe | F5: 46316
A6: Concluído | B6: S0-03 Elaborar os mapas mentais de ideias e de requisitos | C6: Mapa mental no Coggle | D6: Sprint 0 | E6: Equipe | F6: 46316
A7: Concluído | B7: S0-04 Elencar os requisitos do cliente e os requisitos funcionais e não funcionais | C7: RF01 a RF18 e RNF01 a RNF16, com ISO/IEC 25010 | D7: Sprint 0 | E7: Equipe | F7: 46316
A8: Concluído | B8: S0-05 Elaborar a modelagem UML (casos de uso, sequência e estados) | C8: Diagramas UML documentados | D8: Sprint 0 | E8: Equipe | F8: 46316
A9: Concluído | B9: S0-06 Modelar o processo de atendimento em BPMN | C9: Processo com raias: Cliente, Recepcionista, Mecânico e Sistema | D9: Sprint 0 | E9: Equipe | F9: 46316
A10: Em andamento | B10: S0-07 Montar o backlog do produto, o backlog da sprint e o quadro Kanban no Trello | C10: Excel de apoio + quadro no Trello | D10: Sprint 0 | E10: Equipe | F10: 46316
A11: Em andamento | B11: S0-08 Preparar a apresentação do planejamento Scrum | C11: PPTX com os prints do Trello | D11: Sprint 0 | E11: Equipe | F11: 46316
A12: Backlog da Sprint | B12: [3] PB01 Configurar ambiente, Git e banco | C12: Como time, quero configurar o ambiente, o repositório e o banco de dados, para começar a desenvolver com a base organizada. Requisitos: RNF14 Prioridade: Alta | D12: Sprint 1 | E12: Gustavo Lona | F12: 46323 | G12: Criar repositório Git e definir branches (main, dev e feature) Configurar o ambiente e o projeto em camadas (apresentação, regras de negócio e dados) Criar o banco de dados e o script de migração inicial
A13: Backlog da Sprint | B13: [3] PB02 Modelar o banco de dados | C13: Como time, quero modelar o banco de dados, para guardar clientes, veículos, OS, peças e contas de forma consistente. Requisitos: RF02, RF03, RF06, RF13, RF16 Prioridade: Alta | D13: Sprint 1 | E13: Pedro Moraes | F13: 46323 | G13: Elaborar o DER (cliente, veículo, OS, peça, funcionário e conta) Criar o dicionário de dados e os scripts DDL Revisar o modelo com a equipe
A14: Backlog da Sprint | B14: [5] PB03 Login e autenticação | C14: Como funcionário, quero fazer login com usuário e senha, para acessar apenas as telas do meu perfil. Requisitos: RF01, RNF10, RNF11 Prioridade: Alta | D14: Sprint 1 | E14: Gustavo Lona | F14: 46323 | G14: Criar a tela de login e a validação de credenciais Implementar hash de senha (bcrypt), sessão de 30 min e bloqueio após 5 tentativas Controlar o acesso às telas por perfil (Recepcionista, Mecânico e Administrador)
A15: Backlog da Sprint | B15: [3] PB04 Cadastro de funcionários e perfis | C15: Como administrador, quero cadastrar funcionários e definir o perfil de cada um, para que cada pessoa veja só o que é da sua função. Requisitos: RF18, RF01 Prioridade: Média | D15: Sprint 1 | E15: Pedro Moraes | F15: 46323 | G15: Criar o cadastro de funcionários (incluir, alterar e inativar) Atribuir o perfil de acesso ao funcionário Bloquear o login de funcionário inativado
A16: Backlog da Sprint | B16: [5] PB05 Cadastro de clientes | C16: Como recepcionista, quero cadastrar clientes com nome, CPF e telefone, para ter os dados à mão nos próximos atendimentos. Requisitos: RF02, RNF05 Prioridade: Alta | D16: Sprint 1 | E16: Alan Filipe | F16: 46323 | G16: Criar a tela de cadastro com validação de CPF e campos obrigatórios Implementar busca por nome ou CPF, edição e inativação Testar os cenários (CPF duplicado e campo vazio)
A17: Backlog da Sprint | B17: [5] PB06 Cadastro de veículos | C17: Como recepcionista, quero cadastrar veículos vinculados a um cliente, para identificar rápido qual carro está sendo atendido. Requisitos: RF03, RNF05 Prioridade: Alta | D17: Sprint 1 | E17: Alan Filipe | F17: 46323 | G17: Criar o cadastro de veículo vinculado ao cliente, com validação de placa (padrão antigo e Mercosul) Tratar placa já cadastrada e transferência de proprietário Testar os cenários de placa inválida e duplicada
A18: Backlog do Produto | B18: [8] PB07 Abrir Ordem de Serviço | C18: Como recepcionista, quero abrir uma OS informando placa, km e problema relatado, para registrar a entrada do veículo. Requisitos: RF06, RNF03, RNF09 Prioridade: Alta | D18: Sprint 2 | E18: Gustavo Lona | F18: 46330 | G18: Criar a busca por placa e a exibição dos dados do veículo e do cliente Criar o formulário de abertura (km, problema relatado e número sequencial da OS) Implementar as regras: OS em andamento, km menor que a anterior e rascunho automático
A19: Backlog do Produto | B19: [5] PB08 Checklist de entrada | C19: Como recepcionista, quero registrar o checklist de entrada, para evitar discussões sobre danos que já existiam. Requisitos: RF07 Prioridade: Alta | D19: Sprint 2 | E19: Pedro Moraes | F19: 46330 | G19: Criar a tela de checklist (avarias, combustível e itens presentes) Vincular o checklist à OS e torná-lo obrigatório Testar o preenchimento e a obrigatoriedade
A20: Backlog do Produto | B20: [3] PB09 Histórico do veículo | C20: Como mecânico, quero consultar o histórico de serviços de um veículo pela placa, para diagnosticar com base nas manutenções anteriores. Requisitos: RF04 Prioridade: Média | D20: Sprint 2 | E20: Alan Filipe | F20: 46330 | G20: Criar a consulta de OS por placa, da mais recente para a mais antiga Tratar os casos sem histórico e placa não encontrada Testar os três cenários de consulta
A21: Backlog do Produto | B21: [5] PB10 Agenda de atendimentos | C21: Como recepcionista, quero agendar, reagendar e cancelar atendimentos, para organizar a entrada de carros e evitar lotação dos boxes. Requisitos: RF05 Prioridade: Média | D21: Sprint 2 | E21: Alan Filipe | F21: 46330 | G21: Criar a agenda e o agendamento por horário Implementar o limite de boxes e a sugestão de horários livres Implementar o reagendamento e o cancelamento
A22: Backlog do Produto | B22: [5] PB15 Cadastro de peças | C22: Como administrador, quero cadastrar peças com código, preços, quantidade e estoque mínimo, para ter o estoque organizado. Requisitos: RF13 Prioridade: Alta | D22: Sprint 2 | E22: Pedro Moraes | F22: 46330 | G22: Criar o cadastro de peças (código, descrição, custo, venda, quantidade e mínimo) Validar código duplicado e preço de venda abaixo do custo Criar a busca de peças para uso no orçamento
A23: Backlog do Produto | B23: [8] PB11 Orçamento da OS | C23: Como mecânico, quero montar o orçamento da OS com peças e mão de obra, para que o cliente saiba o valor antes de autorizar. Requisitos: RF08 Prioridade: Alta | D23: Sprint 3 | E23: Gustavo Lona | F23: 46337 | G23: Criar a tela de orçamento com itens de peças e mão de obra Calcular os totais e avisar quando o estoque for insuficiente Tratar orçamento vazio e mudar a OS para Aguardando aprovação
... A33: Backlog do Produto | B33: [3] PB23 Entrega final e apresentação | C33: Como time, quero preparar a entrega final, para apresentar o sistema funcionando. Requisitos: - Prioridade: Média | D33: Sprint 4 | E33: Pedro Moraes | F33: 46344 | G33: Publicar o sistema em ambiente de apresentação Preparar o material de apoio ao usuário Ensaiar a apresentação final
A34: Backlog do Produto | B34: [5] PB22 Backup e auditoria | C34: Como administrador, quero backup automático e registro de auditoria, para recuperar dados e saber quem alterou o quê. Requisitos: RNF08, RNF12 Prioridade: Baixa | D34: Sem sprint | E34: A definir | G34: Configurar o backup automático diário do banco Registrar auditoria de OS, estoque e financeiro Testar a restauração do backup

Sheet Guia Trello
A1: Como montar o quadro Kanban no Trello
A3: Passo | B3: O que fazer
A4: 1. Criar o quadro | B4: No Trello, clique em Criar > Criar quadro. Nome: Overdrive - Scrum. Convide Alan, Gustavo e Pedro pelo e-mail.
A5: 2. Criar as 5 listas | B5: Backlog do Produto | Backlog da Sprint | Em andamento | Em revisão | Concluído (nessa ordem, da esquerda para a direita).
A6: 3. Criar as etiquetas | B6: Menu do quadro > Etiquetas: Sprint 0, Sprint 1, Sprint 2, Sprint 3, Sprint 4 e Sem sprint. Use uma cor por sprint.
A7: 4. Colar os cartões | B7: Na aba Cartões Trello, filtre a coluna Lista (ex.: Backlog do Produto), copie as células da coluna Título e cole em 'Adicionar um cartão' da lista correspondente. O Trello cria um cartão por linha.
A8: 5. Completar cada cartão | B8: Abra o cartão e cole a Descrição, adicione a Etiqueta, o Membro e a Data de entrega. Em Checklist, cole a coluna Checklist: cada linha vira um item.
A9: 6. Regra do Kanban (WIP) | B9: Máximo de 2 cartões por pessoa em Em andamento. Um cartão só vai para Concluído depois de passar por Em revisão (aceite do Product Owner).
A10: 7. Rotina de cada sprint | B10: Planning: mover os cartões da sprint para Backlog da Sprint. Daily: atualizar o quadro. Review: cartões aceitos vão para Concluído. Retrospective: registrar melhorias (cartão ou aba Cerimônias).
A11: 8. Prints para a entrega | B11: Tire prints do quadro inteiro, de um cartão aberto (com checklist, membro e data) e do quadro por sprint (filtro por etiqueta). Cole nos slides do PPTX.
